{
  "schema": "wordbank-reviewed@1",
  "slug": "g1-u03",
  "round": 1,
  "rows": {
    "finger": "3e8f3d286880",
    "ear": "997f8d9186e3",
    "nose": "b520f2fd6031",
    "hair": "2fbf69400c43",
    "eye": "7538d0e0c71e",
    "mouth": "413814efa26a",
    "beard": "885ce962b3bc",
    "right-arm": "ce86b569861f",
    "left-arm": "a14ba71338ef",
    "shoulder": "b51c6a30637e",
    "leg": "2b3187b89980",
    "foot": "39a79365188e",
    "feet": "64e34cd483c7",
    "tooth": "1bf01ae6e914",
    "teeth": "d9c815acbd89",
    "tall": "9f447d52254e",
    "short": "7b0f3682c99e",
    "big": "bd3ed5247126",
    "small": "1f8c9e2843e7",
    "long": "4aa2e86e7cdd",
    "also": "526458334b00",
    "famous": "6b400d9bd1cc",
    "him": "4675522ffbc0",
    "his": "78ada87af4e2",
    "ship": "7057c607d75f",
    "to-be-scared": "0efacd10ba45",
    "strong": "f2f2d96f5347",
    "captain": "beeffbe3804b",
    "have-got-has-got": "e41f9b47e0e4",
    "pretty": "4de091dbe7f6",
    "purple": "19d1c3d6c2d2",
    "week": "9392a41c8904",
    "again": "2c33fceb3041",
    "back": "5421fe6416fe",
    "to-paint": "60ba2c1a9de0",
    "sister": "164acb7fd425",
    "boy": "939b0cbd004e",
    "girl": "0534c9201567",
    "man": "d0f1eb7e4fea",
    "woman": "b8889770a576",
    "her-name-is": "6de1288fce34",
    "his-name-is": "5faf65488145"
  }
}
