{
  "schema": "cast@1",
  "storyId": "g1.st.lost-pages",
  "members": [
    {
      "id": "finn",
      "nameEn": "Finn",
      "descriptionDe": "Dein Freund aus dem Buch",
      "voice": null,
      "art": null
    },
    {
      "id": "berger",
      "nameEn": "Frau Berger",
      "descriptionDe": "die Lehrerin",
      "voice": null,
      "art": null
    },
    {
      "id": "guide",
      "nameEn": "Zoo Guide",
      "descriptionDe": "die Zooführerin",
      "voice": null,
      "art": null
    },
    {
      "id": "captain",
      "nameEn": "Captain",
      "descriptionDe": "der Kapitän",
      "voice": null,
      "art": null
    },
    {
      "id": "pixel",
      "nameEn": "Pixel",
      "descriptionDe": "die Katze aus dem Buch",
      "voice": null,
      "art": null
    },
    {
      "id": "robo",
      "nameEn": "Robo",
      "descriptionDe": "der kleine Roboter",
      "voice": null,
      "art": null
    },
    {
      "id": "anna",
      "nameEn": "Anna",
      "descriptionDe": "die Schlagzeugerin",
      "voice": null,
      "art": null
    },
    {
      "id": "mo",
      "nameEn": "Detective Mo",
      "descriptionDe": "der Detektiv",
      "voice": null,
      "art": null
    },
    {
      "id": "luca",
      "nameEn": "Chef Luca",
      "descriptionDe": "der Koch",
      "voice": null,
      "art": null
    },
    {
      "id": "mila",
      "nameEn": "Mila",
      "descriptionDe": "das Mädchen mit der Kleidung",
      "voice": null,
      "art": null
    },
    {
      "id": "tim",
      "nameEn": "Professor Tim",
      "descriptionDe": "der Haustier-Professor",
      "voice": null,
      "art": null
    },
    {
      "id": "apple",
      "nameEn": "Mrs Apple",
      "descriptionDe": "die Verkäuferin",
      "voice": null,
      "art": null
    },
    {
      "id": "tik",
      "nameEn": "Tik the Clockmaker",
      "descriptionDe": "der Uhrmacher",
      "voice": null,
      "art": null
    },
    {
      "id": "rosa",
      "nameEn": "Omi Rosa",
      "descriptionDe": "die Oma mit dem Geburtstag",
      "voice": null,
      "art": null
    },
    {
      "id": "sam",
      "nameEn": "Emergency Sam",
      "descriptionDe": "der Held vom Notdienst",
      "voice": null,
      "art": null
    },
    {
      "id": "peppi",
      "nameEn": "DJ Peppi",
      "descriptionDe": "der DJ",
      "voice": null,
      "art": null
    },
    {
      "id": "jona",
      "nameEn": "Jona",
      "descriptionDe": "Der Junge aus dem Buch",
      "voice": null,
      "art": null
    },
    {
      "id": "voice",
      "nameEn": "A voice",
      "descriptionDe": "Eine Stimme aus dem Buch",
      "voice": null,
      "art": null
    }
  ]
}