{
  "schema": "items-reviewed@1",
  "slug": "g1-u09",
  "round": 1,
  "rows": {
    "a-day": "5005585dc015",
    "a-week": "a5431c7dfef8",
    "across": "0a2aa826f05e",
    "aunty": "00f2b6a79fa9",
    "basket": "db1b3c67e12a",
    "bat": "5f2298bfda93",
    "beginning": "496ebd0eab6b",
    "best-wishes": "42f6045e1671",
    "box": "b9d8031b944f",
    "budgie": "63f9a33bfc8b",
    "cage": "b85dcd020399",
    "camel": "8a7fc61aa9b0",
    "cuddly-toy": "0be2261c6c34",
    "dangerous": "4dac541ca062",
    "daughter": "a156b85d6ef4",
    "dear": "23b74e19057e",
    "elephant": "5f808d9baa4a",
    "ending": "32c3d3d04f63",
    "everybody": "272600e6745e",
    "far-away": "86491824053d",
    "farm": "4f0508743687",
    "fish": "50bcf9cb53bc",
    "fur": "6940c9b91c04",
    "grandpa": "f24b35c3abe0",
    "guinea-pig": "46de3eb7bc4e",
    "letter": "33d3a1ab15a3",
    "lizard": "e373436c1f43",
    "man": "027c365b4e5d",
    "mother": "6ddba82d08ab",
    "mouse": "b5533e22dba4",
    "mouse-2": "f7fab09be481",
    "near": "8a6a5bd47c44",
    "newspaper": "e16ff66c29ae",
    "noise": "2954f93e246b",
    "once": "7837433b8348",
    "owl": "1d9fd69eda14",
    "owner": "c5b03d0aaf80",
    "personal": "ac7e555df9d4",
    "pig": "40f36d64b5ec",
    "pony": "51400b34accb",
    "rabbit": "20b00006aaa0",
    "rat": "176b6da6b075",
    "shark": "2cbc17a69412",
    "spider": "033e0eb4e649",
    "tank": "d08289ba4a6b",
    "terrarium": "22220f9e9cf6",
    "to-be-interested-in": "30782a1d714e",
    "to-begin": "5bf11a150d29",
    "to-bite": "feb53c9d5b2c",
    "to-drive": "1efdae3be846",
    "to-need": "bf06977b1993",
    "to-stay": "06f154addc14",
    "to-visit": "8b98991597e9",
    "tortoise": "c3ffc4e17702",
    "twice": "b434b37e5bfe",
    "unusual": "acffa080bb22",
    "zebra": "0d23280d71b1",
    "irregular-plurals-3.ag.002": "22f4398304d7",
    "irregular-plurals-3.cp.001": "f38b9fa6b222",
    "irregular-plurals-3.ec.001": "33e24511d1df",
    "irregular-plurals-3.ec.002": "e5dc8592f1fc",
    "irregular-plurals-3.gf.001": "efdb57788c11",
    "irregular-plurals-3.gf.002": "864220481326",
    "irregular-plurals-3.gf.003": "ee93cb119e8e",
    "irregular-plurals-3.mc.001": "07335d9c9f5c",
    "irregular-plurals-3.mc.002": "dae3d12935e2",
    "irregular-plurals-3.sb.001": "e0b14879289e",
    "irregular-plurals-3.tf.001": "5daeb8692603",
    "irregular-plurals-3.tf.002": "e8d903d1302a",
    "irregular-plurals-3.tr.001": "f17edc0fa9e3",
    "object-pronouns.ag.003": "f6ef5c71efe0",
    "object-pronouns.ag.004": "5b453ab4443c",
    "object-pronouns.cp.001": "0fe24642062a",
    "object-pronouns.cp.002": "9ebae106a5a5",
    "object-pronouns.ec.001": "0b0e492dcb0f",
    "object-pronouns.ec.002": "7f1a1edacf76",
    "object-pronouns.ec.003": "f435c84f92a5",
    "object-pronouns.gf.001": "30fb7f13c63b",
    "object-pronouns.gf.003": "085323ad1174",
    "object-pronouns.gf.004": "0322ea4ef181",
    "object-pronouns.gf.005": "8018faaed1e3",
    "object-pronouns.gf.006": "9010091ef774",
    "object-pronouns.gf.007": "480324ac4652",
    "object-pronouns.gs.002": "7e54b8729767",
    "object-pronouns.mc.001": "3e8598d03a81",
    "object-pronouns.mc.002": "28e36144228c",
    "object-pronouns.mc.003": "301271a5d581",
    "object-pronouns.mt.002": "02c860ca7084",
    "object-pronouns.mt.003": "ae118cac313f",
    "object-pronouns.sb.001": "2db582e2bae0",
    "object-pronouns.sb.002": "dabb2c35b5bd",
    "object-pronouns.tf.001": "f4c19f56f042",
    "object-pronouns.tf.002": "e730bac2fda2",
    "object-pronouns.tf.003": "c4391e004c0d",
    "object-pronouns.tr.001": "932f22612f45",
    "object-pronouns.tr.002": "d50af9abd1a0",
    "possessive-s.ag.004": "cea74a4e2e95",
    "possessive-s.ag.005": "4c45811192fa",
    "possessive-s.cp.001": "be72e39418d7",
    "possessive-s.ec.001": "580ede0a2257",
    "possessive-s.ec.003": "6743b2fe5a3c",
    "possessive-s.ec.004": "2504ed3d6987",
    "possessive-s.gf.001": "7b2b49050088",
    "possessive-s.gf.002": "cca8ef824861",
    "possessive-s.gf.003": "ca3317ba1e79",
    "possessive-s.gf.004": "e2b85f866c8a",
    "possessive-s.gf.005": "dc17c8586f74",
    "possessive-s.gf.006": "7252ebe775dd",
    "possessive-s.gf.007": "213d4bfb18b4",
    "possessive-s.gs.002": "b62e7043fdbc",
    "possessive-s.mc.001": "7f06a6f22cc0",
    "possessive-s.mc.002": "4b7b6dec538e",
    "possessive-s.mc.004": "8e8101d9648a",
    "possessive-s.mp.001": "73ad57762b05",
    "possessive-s.mt.001": "7b71bf3535ea",
    "possessive-s.sb.001": "0b7127548abd",
    "possessive-s.sb.002": "e1e7e8cd3c89",
    "possessive-s.tf.001": "00f9301548c9",
    "possessive-s.tf.002": "635d86eca06b",
    "possessive-s.tf.003": "b2c4bcd90fff",
    "possessive-s.tr.002": "134f17174b46",
    "possessive-s.tr.003": "f31af07fe10c",
    "question-words.ag.001": "c44824cff5a4",
    "question-words.cp.001": "202dfac5d200",
    "question-words.cp.002": "03f7b61af627",
    "question-words.ec.001": "8015c30b7eb0",
    "question-words.ec.002": "86ccef35f215",
    "question-words.ec.003": "879a3ca00db3",
    "question-words.gf.001": "01dff30d9d93",
    "question-words.gf.002": "90f1b1190f31",
    "question-words.gf.003": "d08058acface",
    "question-words.gf.004": "158fb98a50ba",
    "question-words.gs.001": "efd780d6f317",
    "question-words.mc.001": "c038741fae69",
    "question-words.mc.002": "ea1e17e3ac8b",
    "question-words.mc.003": "128d51e42235",
    "question-words.mp.001": "79b39ea9b230",
    "question-words.mt.001": "ebae758c5816",
    "question-words.qf.001": "fac871d8dfbb",
    "question-words.qf.002": "5634f2942f36",
    "question-words.sb.001": "ba342c738d47",
    "question-words.sb.002": "72f7c030b6e2",
    "question-words.tf.001": "ac64ca1400fb",
    "question-words.tf.003": "69303a4dd444",
    "question-words.tr.001": "dc7bb5a89400",
    "question-words.tr.002": "6a2a78336136"
  }
}
